master_password/__init__.py
master_password/auth/__init__.py
master_password/auth/backends.py
master_password_django-1.0.dist-info/LICENCE
master_password_django-1.0.dist-info/METADATA
master_password_django-1.0.dist-info/WHEEL
master_password_django-1.0.dist-info/top_level.txt
master_password_django-1.0.dist-info/RECORD
